WangfengShiwen2130/README.md
WangfengShiwen2130/__init__.py
WangfengShiwen2130/__main__.py
WangfengShiwen2130/file.epub
WangfengShiwen2130/index.html
WangfengShiwen2130/css/__init__.py
WangfengShiwen2130/css/annotations.css
WangfengShiwen2130/css/main.css
WangfengShiwen2130/css/normalize.css
WangfengShiwen2130/css/popup.css
WangfengShiwen2130/font/__init__.py
WangfengShiwen2130/font/fontello.eot
WangfengShiwen2130/font/fontello.svg
WangfengShiwen2130/font/fontello.ttf
WangfengShiwen2130/font/fontello.woff
WangfengShiwen2130/img/__init__.py
WangfengShiwen2130/img/annotator-glyph-sprite.png
WangfengShiwen2130/img/annotator-icon-sprite.png
WangfengShiwen2130/img/apple-touch-icon.png
WangfengShiwen2130/img/cancelfullscreen.png
WangfengShiwen2130/img/close.png
WangfengShiwen2130/img/fullscreen.png
WangfengShiwen2130/img/loader.gif
WangfengShiwen2130/img/menu-icon.png
WangfengShiwen2130/img/save.png
WangfengShiwen2130/img/saved.png
WangfengShiwen2130/img/settings-s.png
WangfengShiwen2130/img/settings.png
WangfengShiwen2130/img/star.png
WangfengShiwen2130/js/__init__.py
WangfengShiwen2130/js/epub.js
WangfengShiwen2130/js/epub.min.js
WangfengShiwen2130/js/epub.min.map
WangfengShiwen2130/js/hooks.min.js
WangfengShiwen2130/js/hooks.min.map
WangfengShiwen2130/js/reader.js
WangfengShiwen2130/js/reader.js.map
WangfengShiwen2130/js/reader.min.js
WangfengShiwen2130/js/reader.min.map
WangfengShiwen2130/js/hooks/__init__.py
WangfengShiwen2130/js/hooks/extensions/__init__.py
WangfengShiwen2130/js/hooks/extensions/highlight.js
WangfengShiwen2130/js/libs/__init__.py
WangfengShiwen2130/js/libs/jquery.min.js
WangfengShiwen2130/js/libs/localforage.min.js
WangfengShiwen2130/js/libs/screenfull.js
WangfengShiwen2130/js/libs/screenfull.min.js
WangfengShiwen2130/js/libs/zip.min.js
WangfengShiwen2130/js/plugins/__init__.py
WangfengShiwen2130/js/plugins/hypothesis.js
WangfengShiwen2130/js/plugins/search.js
wangfeng_shiwen_21_30-2024.3.5.0.dist-info/METADATA
wangfeng_shiwen_21_30-2024.3.5.0.dist-info/WHEEL
wangfeng_shiwen_21_30-2024.3.5.0.dist-info/entry_points.txt
wangfeng_shiwen_21_30-2024.3.5.0.dist-info/top_level.txt
wangfeng_shiwen_21_30-2024.3.5.0.dist-info/RECORD
